azqueuemanager_rss/__init__.py
azqueuemanager_rss-0.0.2.dist-info/LICENSE
azqueuemanager_rss-0.0.2.dist-info/METADATA
azqueuemanager_rss-0.0.2.dist-info/WHEEL
azqueuemanager_rss-0.0.2.dist-info/top_level.txt
azqueuemanager_rss-0.0.2.dist-info/RECORD
