Metadata-Version: 2.1
Name: azqueuemanager-rss
Version: 0.0.2
Summary: rss-parser for AZQueueManager
License: MIT
Keywords: azqueuemanager,extension,rss,azure storage queues
Classifier: Programming Language :: Python :: 3
Requires-Python: >=3.10
License-File: LICENSE
Requires-Dist: azqueuemanager
Requires-Dist: feedparser
Requires-Dist: dateparser
